cheeseshop/__init__.py
cheeseshop-0.0.0.dist-info/METADATA
cheeseshop-0.0.0.dist-info/WHEEL
cheeseshop-0.0.0.dist-info/top_level.txt
cheeseshop-0.0.0.dist-info/RECORD
