Metadata-Version: 2.1
Name: cheeseshop
Version: 0.0.0
Summary: place holder
Home-page: http://github.com/SK/cheeseshop
Author: sking
Author-email: flyingcircus@example.com
License: MIT
